autonomous_agent_hub/__init__.py
agent_hub-0.0.1.dist-info/LICENSE
agent_hub-0.0.1.dist-info/METADATA
agent_hub-0.0.1.dist-info/WHEEL
agent_hub-0.0.1.dist-info/top_level.txt
agent_hub-0.0.1.dist-info/RECORD
