Metadata-Version: 2.1
Name: agent-hub
Version: 0.0.1
Summary: A Python library for creating and managing LLM powered autonomous agents.
Author-email: Shaun Wei <shawnweix@gmail.com>
License: Copyright (c) 2023 Shaun Wei
Project-URL: Source, https://github.com/Shaunwei/AutonomousAgentHub
Project-URL: Homepage, https://github.com/Shaunwei/AutonomousAgentHub
Classifier: Development Status :: 3 - Alpha
Classifier: License :: OSI Approved :: MIT License
Classifier: Programming Language :: Python :: 3
Classifier: Programming Language :: Python :: 3.6
Classifier: Programming Language :: Python :: 3.7
Classifier: Programming Language :: Python :: 3.8
License-File: LICENSE
